Metadata-Version: 1.0
Name: counting-three-dijit
Version: 0.2
Summary: counting random number a, b, and c
Home-page: UNKNOWN
Author: rachid_amk
Author-email: rachid.drid@gmail.com
License: UNKNOWN
Platform: UNKNOWN
